src/__init__.py
src/pymanagebac.py
pymanagebac-0.0.3.dist-info/LICENCE
pymanagebac-0.0.3.dist-info/METADATA
pymanagebac-0.0.3.dist-info/WHEEL
pymanagebac-0.0.3.dist-info/top_level.txt
pymanagebac-0.0.3.dist-info/RECORD
