Metadata-Version: 2.1
Name: pymanagebac
Version: 0.0.3
Summary: A python module for interacting with Managebac using selenium.
Home-page: https://github.com/supermikea/pymanagebac
Author: Mike Wiegman Avila
Author-email: mike12wiegman@gmail.com
License: gplv3
Keywords: managebac,selenium,api,scraping
Classifier: Development Status :: 3 - Alpha
Classifier: Intended Audience :: Developers
Classifier: Programming Language :: Python :: 3
License-File: LICENCE
Requires-Dist: selenium
Requires-Dist: bs4
